KernelAVO/__init__.py
KernelAVO/modulo.py
KernelAVO-0.1.dist-info/METADATA
KernelAVO-0.1.dist-info/WHEEL
KernelAVO-0.1.dist-info/top_level.txt
KernelAVO-0.1.dist-info/RECORD
